gee_s1_processing/__init__.py
gee_s1_processing/border_noise_correction.py
gee_s1_processing/helper.py
gee_s1_processing/speckle_filter.py
gee_s1_processing/terrain_flattening.py
gee_s1_processing/wrapper.py
gee_s1_processing-0.1.0.dist-info/licenses/LICENSE
gee_s1_processing-0.1.0.dist-info/WHEEL
gee_s1_processing-0.1.0.dist-info/METADATA
gee_s1_processing-0.1.0.dist-info/RECORD
