Metadata-Version: 2.4
Name: gee_s1_processing
Version: 0.1.0
Summary: S1 processing package.
Requires-Python: >=3.10
Classifier: Intended Audience :: Developers
Classifier: License :: OSI Approved :: MIT License
Classifier: Operating System :: OS Independent
Classifier: Programming Language :: Python
License-File: LICENSE
Requires-Dist: earthengine-api>=1.6.6
Requires-Dist: dotenv ; extra == "dev"
Requires-Dist: pytest ; extra == "dev"
Requires-Dist: pre-commit ; extra == "dev"
Requires-Dist: ruff ; extra == "dev"
Requires-Dist: types-retry ; extra == "dev"
Requires-Dist: types-requests ; extra == "dev"
Requires-Dist: pydoclint[flake8] ; extra == "dev"
Project-URL: source, https://github.com/LSCE-forest/gee_s1_processing
Project-URL: tracker, https://github.com/LSCE-forest/gee_s1_processing/issues
Provides-Extra: dev
